[{"id":"100","label":"os. Czecha 73","address":"os. Czecha 73","city":"Poznań","longitude":16.977316,"latitude":52.385886,"popupLines":["Poniedziałek: 06:00-23:00<br/>Wtorek: 06:00-23:00<br/>Środa: 06:00-23:00<br/>Czwartek: 06:00-23:00<br/>Piątek: 06:00-23:00<br/>Sobota: 06:00-23:00<br/>Niedziela: Nieczynne"]},{"id":"101","label":"Książęca 1","address":"Książęca 1","city":"Poznań","longitude":16.931766,"latitude":52.366346,"popupLines":["Poniedziałek: 06:00-23:30<br/>Wtorek: 06:00-23:30<br/>Środa: 06:00-23:30<br/>Czwartek: 06:00-23:30<br/>Piątek: 06:00-23:30<br/>Sobota: 06:00-23:30<br/>Niedziela: Nieczynne"]},{"id":"1018","label":"Polanka 22","address":"Polanka 22","city":"Poznań","longitude":16.960846,"latitude":52.399002,"popupLines":["Poniedziałek: 06:00-23:30<br/>Wtorek: 06:00-23:30<br/>Środa: 06:00-23:30<br/>Czwartek: 06:00-23:30<br/>Piątek: 06:00-23:30<br/>Sobota: 06:00-23:30<br/>Niedziela: Nieczynne"]},{"id":"102","label":"Starołęcka 1","address":"Starołęcka 1","city":"Poznań","longitude":16.943854,"latitude":52.378503,"popupLines":["Poniedziałek: 06:00-23:45<br/>Wtorek: 00:00-00:00<br/>Środa: 00:00-00:00<br/>Czwartek: 00:00-00:00<br/>Piątek: 00:00-00:00<br/>Sobota: 00:00-00:00<br/>Niedziela: 09:00-20:00"]},{"id":"1020","label":"Czechosłowacka 104","address":"Czechosłowacka 104","city":"Poznań","longitude":16.893918,"latitude":52.375603,"popupLines":["Poniedziałek: 06:00-23:00<br/>Wtorek: 06:00-23:00<br/>Środa: 06:00-23:00<br/>Czwartek: 06:00-23:00<br/>Piątek: 06:00-23:00<br/>Sobota: 06:00-23:00<br/>Niedziela: 08:00-21:00"]},{"id":"1058","label":"Stare Żegrze 15","address":"Stare Żegrze 15","city":"Poznań","longitude":16.963112,"latitude":52.381833,"popupLines":["Poniedziałek: 06:00-22:30<br/>Wtorek: 06:00-22:30<br/>Środa: 06:00-22:30<br/>Czwartek: 06:00-22:30<br/>Piątek: 06:00-22:30<br/>Sobota: 06:00-22:30<br/>Niedziela: Nieczynne"]},{"id":"1090","label":"Chojnicka 72/74","address":"Chojnicka 72/74","city":"Poznań","longitude":16.789775,"latitude":52.475102,"popupLines":["Poniedziałek: 06:00-22:30<br/>Wtorek: 06:00-22:30<br/>Środa: 06:00-22:30<br/>Czwartek: 06:00-22:30<br/>Piątek: 06:00-22:30<br/>Sobota: 06:00-22:30<br/>Niedziela: Nieczynne"]},{"id":"111","label":"os. Zwycięstwa 110","address":"os. Zwycięstwa 110","city":"Poznań","longitude":16.922273,"latitude":52.438138,"popupLines":["Poniedziałek: 06:00-22:30<br/>Wtorek: 06:00-22:30<br/>Środa: 06:00-22:30<br/>Czwartek: 06:00-22:30<br/>Piątek: 06:00-22:30<br/>Sobota: 06:00-22:30<br/>Niedziela: Nieczynne"]},{"id":"112","label":"os. Bolesława Chrobrego 110","address":"os. Bolesława Chrobrego 110","city":"Poznań","longitude":16.914707,"latitude":52.45237,"popupLines":["Poniedziałek: 06:30-23:30<br/>Wtorek: 06:30-23:30<br/>Środa: 06:30-23:30<br/>Czwartek: 06:30-23:30<br/>Piątek: 06:30-23:30<br/>Sobota: 06:30-23:30<br/>Niedziela: Nieczynne"]},{"id":"1126","label":"Dolna Wilda 104/106","address":"Dolna Wilda 104/106","city":"Poznań","longitude":16.921806,"latitude":52.384092,"popupLines":["Poniedziałek: 06:00-23:30<br/>Wtorek: 06:00-23:30<br/>Środa: 06:00-23:30<br/>Czwartek: 06:00-23:30<br/>Piątek: 06:00-23:30<br/>Sobota: 06:00-23:30<br/>Niedziela: Nieczynne"]},{"id":"113","label":"Święty Marcin 66/72","address":"Święty Marcin 66/72","city":"Poznań","longitude":16.921824,"latitude":52.407276,"popupLines":["Poniedziałek: 06:00-22:00<br/>Wtorek: 06:00-22:00<br/>Środa: 06:00-22:00<br/>Czwartek: 06:00-22:00<br/>Piątek: 06:00-22:00<br/>Sobota: 06:00-22:00<br/>Niedziela: Nieczynne"]},{"id":"1133","label":"os. Bolesława Śmiałego 109","address":"os. Bolesława Śmiałego 109","city":"Poznań","longitude":16.92275,"latitude":52.45181,"popupLines":["Poniedziałek: 06:30-23:30<br/>Wtorek: 06:30-23:30<br/>Środa: 06:30-23:30<br/>Czwartek: 06:30-23:30<br/>Piątek: 06:30-23:30<br/>Sobota: 06:30-23:30<br/>Niedziela: Nieczynne"]},{"id":"114","label":"Stróżyńskiego 21A","address":"Stróżyńskiego 21A","city":"Poznań","longitude":16.903869,"latitude":52.4577,"popupLines":["Poniedziałek: 06:30-23:30<br/>Wtorek: 06:30-23:30<br/>Środa: 06:30-23:30<br/>Czwartek: 06:30-23:30<br/>Piątek: 06:30-23:30<br/>Sobota: 06:30-23:30<br/>Niedziela: Nieczynne"]},{"id":"1149","label":"Obornicka 334","address":"Obornicka 334","city":"Poznań","longitude":16.89555,"latitude":52.459158,"popupLines":["Poniedziałek: 06:00-22:30<br/>Wtorek: 06:00-22:30<br/>Środa: 06:00-22:30<br/>Czwartek: 06:00-22:30<br/>Piątek: 06:00-22:30<br/>Sobota: 06:00-22:30<br/>Niedziela: 09:00-20:00"]},{"id":"1161","label":"Kazimierza Wielkiego 1/3","address":"Kazimierza Wielkiego 1/3","city":"Poznań","longitude":16.938359,"latitude":52.401495,"popupLines":["Poniedziałek: 06:00-22:30<br/>Wtorek: 06:00-22:30<br/>Środa: 06:00-22:30<br/>Czwartek: 06:00-22:30<br/>Piątek: 06:00-22:30<br/>Sobota: 06:00-22:30<br/>Niedziela: Nieczynne"]},{"id":"1223","label":"Piątkowska 78","address":"Piątkowska 78","city":"Poznań","longitude":16.917857,"latitude":52.428098,"popupLines":["Poniedziałek: 06:00-23:30<br/>Wtorek: 06:00-23:30<br/>Środa: 06:00-23:30<br/>Czwartek: 06:00-23:30<br/>Piątek: 06:00-23:30<br/>Sobota: 06:00-23:30<br/>Niedziela: 09:00-20:00"]},{"id":"123","label":"Jesionowa 16","address":"Jesionowa 16","city":"Poznań","longitude":16.895353,"latitude":52.367135,"popupLines":["Poniedziałek: 06:00-22:00<br/>Wtorek: 06:00-22:00<br/>Środa: 06:00-22:00<br/>Czwartek: 06:00-22:00<br/>Piątek: 06:00-22:00<br/>Sobota: 06:00-22:00<br/>Niedziela: Nieczynne"]},{"id":"124","label":"Czarnieckiego 12","address":"Czarnieckiego 12","city":"Poznań","longitude":16.916745,"latitude":52.392684,"popupLines":["Poniedziałek: 06:00-23:30<br/>Wtorek: 06:00-23:30<br/>Środa: 06:00-23:30<br/>Czwartek: 06:00-23:30<br/>Piątek: 06:00-23:30<br/>Sobota: 06:00-23:30<br/>Niedziela: Nieczynne"]},{"id":"1269","label":"Ściegiennego 64","address":"Ściegiennego 64","city":"Poznań","longitude":16.875798,"latitude":52.389635,"popupLines":["Poniedziałek: 06:00-22:00<br/>Wtorek: 06:00-22:00<br/>Środa: 06:00-22:00<br/>Czwartek: 06:00-22:00<br/>Piątek: 06:00-22:00<br/>Sobota: 06:00-22:00<br/>Niedziela: 08:00-21:00"]},{"id":"1270","label":"Łukaszewicza 43","address":"Łukaszewicza 43","city":"Poznań","longitude":16.902787,"latitude":52.390296,"popupLines":["Poniedziałek: 06:00-23:30<br/>Wtorek: 06:00-23:30<br/>Środa: 06:00-23:30<br/>Czwartek: 06:00-23:30<br/>Piątek: 06:00-23:30<br/>Sobota: 06:00-23:30<br/>Niedziela: 09:00-20:00"]},{"id":"1271","label":"Wojskowa 3","address":"Wojskowa 3","city":"Poznań","longitude":16.892645,"latitude":52.400578,"popupLines":["Poniedziałek: 06:30-23:00<br/>Wtorek: 06:30-23:00<br/>Środa: 06:30-23:00<br/>Czwartek: 06:30-23:00<br/>Piątek: 06:30-23:00<br/>Sobota: 06:30-23:00<br/>Niedziela: 08:00-21:00"]},{"id":"1272","label":"Strzeszyńska 33","address":"Strzeszyńska 33","city":"Poznań","longitude":16.897186,"latitude":52.447272,"popupLines":["Poniedziałek: 06:30-23:30<br/>Wtorek: 06:30-23:30<br/>Środa: 06:30-23:30<br/>Czwartek: 06:30-23:30<br/>Piątek: 06:30-23:30<br/>Sobota: 06:30-23:30<br/>Niedziela: Nieczynne"]},{"id":"1282","label":"os. Rzeczypospolitej 42","address":"os. Rzeczypospolitej 42","city":"Poznań","longitude":16.946731,"latitude":52.386439,"popupLines":["Poniedziałek: 06:00-22:30<br/>Wtorek: 06:00-22:30<br/>Środa: 06:00-22:30<br/>Czwartek: 06:00-22:30<br/>Piątek: 06:00-22:30<br/>Sobota: 06:00-22:30<br/>Niedziela: Nieczynne"]},{"id":"1283","label":"Małachowskiego 14","address":"Małachowskiego 14","city":"Poznań","longitude":16.959435,"latitude":52.413573,"popupLines":["Poniedziałek: 06:00-23:30<br/>Wtorek: 06:00-23:30<br/>Środa: 06:00-23:30<br/>Czwartek: 06:00-23:30<br/>Piątek: 06:00-23:30<br/>Sobota: 06:00-23:30<br/>Niedziela: Nieczynne"]},{"id":"1284","label":"os. Armii Krajowej 101","address":"os. Armii Krajowej 101","city":"Poznań","longitude":16.950792,"latitude":52.379681,"popupLines":["Poniedziałek: 06:00-22:30<br/>Wtorek: 06:00-22:30<br/>Środa: 06:00-22:30<br/>Czwartek: 06:00-22:30<br/>Piątek: 06:00-22:30<br/>Sobota: 06:00-22:30<br/>Niedziela: Nieczynne"]},{"id":"1285","label":"Bobrzańska 13","address":"Bobrzańska 13","city":"Poznań","longitude":16.969027,"latitude":52.386038,"popupLines":["Poniedziałek: 06:00-23:00<br/>Wtorek: 06:00-23:00<br/>Środa: 06:00-23:00<br/>Czwartek: 06:00-23:00<br/>Piątek: 06:00-23:00<br/>Sobota: 06:00-23:00<br/>Niedziela: Nieczynne"]},{"id":"1295","label":"Naramowicka 219","address":"Naramowicka 219","city":"Poznań","longitude":16.946653,"latitude":52.453174,"popupLines":["Poniedziałek: 06:00-23:30<br/>Wtorek: 06:00-23:30<br/>Środa: 06:00-23:30<br/>Czwartek: 06:00-23:30<br/>Piątek: 06:00-23:30<br/>Sobota: 06:00-23:30<br/>Niedziela: Nieczynne"]},{"id":"1296","label":"os. Jana III Sobieskiego 103","address":"os. Jana III Sobieskiego 103","city":"Poznań","longitude":16.90706,"latitude":52.463362,"popupLines":["Poniedziałek: 06:30-23:30<br/>Wtorek: 06:30-23:30<br/>Środa: 06:30-23:30<br/>Czwartek: 06:30-23:30<br/>Piątek: 06:30-23:30<br/>Sobota: 06:30-23:30<br/>Niedziela: Nieczynne"]},{"id":"1306","label":"Żurawinowa 2","address":"Żurawinowa 2","city":"Poznań","longitude":16.904454,"latitude":52.367452,"popupLines":["Poniedziałek: 06:00-22:30<br/>Wtorek: 06:00-22:30<br/>Środa: 06:00-22:30<br/>Czwartek: 06:00-22:30<br/>Piątek: 06:00-22:30<br/>Sobota: 06:00-22:30<br/>Niedziela: Nieczynne"]},{"id":"1307","label":"Wierzbięcice 36","address":"Wierzbięcice 36","city":"Poznań","longitude":16.921997,"latitude":52.394851,"popupLines":["Poniedziałek: 06:00-23:30<br/>Wtorek: 06:00-23:30<br/>Środa: 06:00-23:30<br/>Czwartek: 06:00-23:30<br/>Piątek: 06:00-23:30<br/>Sobota: 06:00-23:30<br/>Niedziela: Nieczynne"]},{"id":"2080","label":"os. Czecha 111","address":"os. Czecha 111","city":"Poznań","longitude":16.982913,"latitude":52.386906,"popupLines":["Poniedziałek: 06:00-23:00<br/>Wtorek: 06:00-23:00<br/>Środa: 06:00-23:00<br/>Czwartek: 06:00-23:00<br/>Piątek: 06:00-23:00<br/>Sobota: 06:00-23:00<br/>Niedziela: Nieczynne"]},{"id":"2248","label":"Józefa Strusia 12","address":"Józefa Strusia 12","city":"Poznań","longitude":16.902506,"latitude":52.397007,"popupLines":["Poniedziałek: Nieczynne<br/>Wtorek: Nieczynne<br/>Środa: Nieczynne<br/>Czwartek: Nieczynne<br/>Piątek: Nieczynne<br/>Sobota: Nieczynne<br/>Niedziela: Nieczynne"]},{"id":"2250","label":"Polna 41","address":"Polna 41","city":"Poznań","longitude":16.893702,"latitude":52.405444,"popupLines":["Poniedziałek: 06:00-22:00<br/>Wtorek: 06:00-22:00<br/>Środa: 06:00-22:00<br/>Czwartek: 06:00-22:00<br/>Piątek: 06:00-22:00<br/>Sobota: 06:00-22:00<br/>Niedziela: 08:00-21:00"]},{"id":"2265","label":"Piaskowa 2/3","address":"Piaskowa 2/3","city":"Poznań","longitude":16.887276,"latitude":52.323783,"popupLines":["Poniedziałek: 06:00-23:30<br/>Wtorek: 06:00-23:30<br/>Środa: 06:00-23:30<br/>Czwartek: 06:00-23:30<br/>Piątek: 06:00-23:30<br/>Sobota: 06:00-23:30<br/>Niedziela: Nieczynne"]},{"id":"2308","label":"Gronowa 26","address":"Gronowa 26","city":"Poznań","longitude":16.934089,"latitude":52.430304,"popupLines":["Poniedziałek: 06:00-22:30<br/>Wtorek: 06:00-22:30<br/>Środa: 06:00-22:30<br/>Czwartek: 06:00-22:30<br/>Piątek: 06:00-22:30<br/>Sobota: 06:00-22:30<br/>Niedziela: Nieczynne"]},{"id":"2331","label":"Sycowska 18","address":"Sycowska 18","city":"Poznań","longitude":16.840605,"latitude":52.367191,"popupLines":["Poniedziałek: 06:00-22:00<br/>Wtorek: 06:00-22:00<br/>Środa: 06:00-22:00<br/>Czwartek: 06:00-22:00<br/>Piątek: 06:00-22:00<br/>Sobota: 06:00-22:00<br/>Niedziela: Nieczynne"]},{"id":"2361","label":"os. Orła Białego 5","address":"os. Orła Białego 5","city":"Poznań","longitude":16.960217,"latitude":52.377586,"popupLines":["Poniedziałek: 06:00-22:30<br/>Wtorek: 06:00-22:30<br/>Środa: 06:00-22:30<br/>Czwartek: 06:00-22:30<br/>Piątek: 06:00-22:30<br/>Sobota: 06:00-22:30<br/>Niedziela: Nieczynne"]},{"id":"2413","label":"Hallera 2a","address":"Hallera 2a","city":"Poznań","longitude":16.872023,"latitude":52.377548,"popupLines":["Poniedziałek: 06:00-22:00<br/>Wtorek: 06:00-22:00<br/>Środa: 06:00-22:00<br/>Czwartek: 06:00-22:00<br/>Piątek: 06:00-22:00<br/>Sobota: 06:00-22:00<br/>Niedziela: Nieczynne"]},{"id":"2414","label":"Lechicka 59","address":"Lechicka 59","city":"Poznań","longitude":16.916175,"latitude":52.443406,"popupLines":["Poniedziałek: 06:00-22:30<br/>Wtorek: 06:00-22:30<br/>Środa: 06:00-22:30<br/>Czwartek: 06:00-22:30<br/>Piątek: 06:00-22:30<br/>Sobota: 06:00-22:30<br/>Niedziela: Nieczynne"]},{"id":"2427","label":"Grunwaldzka 216","address":"Grunwaldzka 216","city":"Poznań","longitude":16.853812,"latitude":52.389611,"popupLines":["Poniedziałek: Nieczynne<br/>Wtorek: Nieczynne<br/>Środa: Nieczynne<br/>Czwartek: Nieczynne<br/>Piątek: Nieczynne<br/>Sobota: Nieczynne<br/>Niedziela: Nieczynne"]},{"id":"2463","label":"Gwiaździsta 30","address":"Gwiaździsta 30","city":"Poznań","longitude":16.867434,"latitude":52.391244,"popupLines":["Poniedziałek: 06:00-23:00<br/>Wtorek: 06:00-23:00<br/>Środa: 06:00-23:00<br/>Czwartek: 06:00-23:00<br/>Piątek: 06:00-23:00<br/>Sobota: 06:00-23:00<br/>Niedziela: 09:00-20:00"]},{"id":"2500","label":"Libelta 5","address":"Libelta 5","city":"Poznań","longitude":16.923002,"latitude":52.410499,"popupLines":["Poniedziałek: 06:00-22:00<br/>Wtorek: 06:00-22:00<br/>Środa: 06:00-22:00<br/>Czwartek: 06:00-22:00<br/>Piątek: 06:00-22:00<br/>Sobota: 06:00-22:00<br/>Niedziela: Nieczynne"]},{"id":"2503","label":"Święty Marcin 32","address":"Święty Marcin 32","city":"Poznań","longitude":16.926218,"latitude":52.406352,"popupLines":["Poniedziałek: 06:00-22:00<br/>Wtorek: 06:00-22:00<br/>Środa: 06:00-22:00<br/>Czwartek: 06:00-22:00<br/>Piątek: 06:00-22:00<br/>Sobota: 06:00-22:00<br/>Niedziela: Nieczynne"]},{"id":"2517","label":"Sielska 43","address":"Sielska 43","city":"Poznań","longitude":16.883107,"latitude":52.386145,"popupLines":["Poniedziałek: 06:00-22:00<br/>Wtorek: 06:00-22:00<br/>Środa: 06:00-22:00<br/>Czwartek: 06:00-22:00<br/>Piątek: 06:00-22:00<br/>Sobota: 06:00-22:00<br/>Niedziela: 08:00-21:00"]},{"id":"2557","label":"28 Czerwca 1956r. 384","address":"28 Czerwca 1956r. 384","city":"Poznań","longitude":16.92993,"latitude":52.40692,"popupLines":["Poniedziałek: 06:00-22:00<br/>Wtorek: 06:00-22:00<br/>Środa: 06:00-22:00<br/>Czwartek: 06:00-22:00<br/>Piątek: 06:00-22:00<br/>Sobota: 06:00-22:00<br/>Niedziela: Nieczynne"]},{"id":"2573","label":"Połabska 1","address":"Połabska 1","city":"Poznań","longitude":16.929796,"latitude":52.4425,"popupLines":["Poniedziałek: 06:00-23:00<br/>Wtorek: 06:00-23:00<br/>Środa: 06:00-23:00<br/>Czwartek: 06:00-23:00<br/>Piątek: 06:00-23:00<br/>Sobota: 06:00-23:00<br/>Niedziela: 09:00-20:00"]},{"id":"2574","label":"Kraszewskiego 30","address":"Kraszewskiego 30","city":"Poznań","longitude":16.901813,"latitude":52.407997,"popupLines":["Poniedziałek: 06:00-22:00<br/>Wtorek: 06:00-22:00<br/>Środa: 06:00-22:00<br/>Czwartek: 06:00-22:00<br/>Piątek: 06:00-22:00<br/>Sobota: 06:00-22:00<br/>Niedziela: Nieczynne"]},{"id":"2617","label":"Naramowicka 104","address":"Naramowicka 104","city":"Poznań","longitude":16.948748,"latitude":52.43916,"popupLines":["Poniedziałek: 06:00-22:00<br/>Wtorek: 06:00-22:00<br/>Środa: 06:00-22:00<br/>Czwartek: 06:00-22:00<br/>Piątek: 06:00-22:00<br/>Sobota: 06:00-22:00<br/>Niedziela: Nieczynne"]},{"id":"2641","label":"Dąbrowskiego 81/85","address":"Dąbrowskiego 81/85","city":"Poznań","longitude":16.898221,"latitude":52.414173,"popupLines":["Poniedziałek: 06:00-22:00<br/>Wtorek: 06:00-22:00<br/>Środa: 06:00-22:00<br/>Czwartek: 06:00-22:00<br/>Piątek: 06:00-22:00<br/>Sobota: 06:00-22:00<br/>Niedziela: Nieczynne"]},{"id":"2729","label":"Półwiejska 47","address":"Półwiejska 47","city":"Poznań","longitude":16.927876,"latitude":52.4002,"popupLines":["Poniedziałek: 06:00-22:00<br/>Wtorek: 06:00-22:00<br/>Środa: 06:00-22:00<br/>Czwartek: 06:00-22:00<br/>Piątek: 06:00-22:00<br/>Sobota: 06:00-22:00<br/>Niedziela: Nieczynne"]},{"id":"2817","label":"ul. Dworcowa 2","address":"ul. Dworcowa 2","city":"Poznań","longitude":17.080276,"latitude":52.446021,"popupLines":["Poniedziałek: 06:00-22:00<br/>Wtorek: 06:00-22:00<br/>Środa: 06:00-22:00<br/>Czwartek: 06:00-22:00<br/>Piątek: 06:00-22:00<br/>Sobota: 06:00-22:00<br/>Niedziela: 08:00-20:00"]},{"id":"3094","label":"Poszwińskiego 2","address":"Poszwińskiego 2","city":"Poznań","longitude":16.867536,"latitude":52.441414,"popupLines":["Poniedziałek: 06:00-22:30<br/>Wtorek: 06:00-22:30<br/>Środa: 06:00-22:30<br/>Czwartek: 06:00-22:30<br/>Piątek: 06:00-22:30<br/>Sobota: 06:00-22:30<br/>Niedziela: 09:00-20:00"]},{"id":"3107","label":"Szwedzka 6a","address":"Szwedzka 6a","city":"Poznań","longitude":16.984935,"latitude":52.381342,"popupLines":["Poniedziałek: 06:00-23:00<br/>Wtorek: 06:00-23:00<br/>Środa: 06:00-23:00<br/>Czwartek: 06:00-23:00<br/>Piątek: 06:00-23:00<br/>Sobota: 06:00-23:00<br/>Niedziela: Nieczynne"]},{"id":"3398","label":"os. Przyjaźni 141","address":"os. Przyjaźni 141","city":"Poznań","longitude":16.921123,"latitude":52.430076,"popupLines":["Poniedziałek: 06:00-23:30<br/>Wtorek: 06:00-23:30<br/>Środa: 06:00-23:30<br/>Czwartek: 06:00-23:30<br/>Piątek: 06:00-23:30<br/>Sobota: 06:00-23:30<br/>Niedziela: Nieczynne"]},{"id":"3600","label":"Serbska 15","address":"Serbska 15","city":"Poznań","longitude":16.945382,"latitude":52.432891,"popupLines":["Poniedziałek: 06:00-22:00<br/>Wtorek: 06:00-22:00<br/>Środa: 06:00-22:00<br/>Czwartek: 06:00-22:00<br/>Piątek: 06:00-22:00<br/>Sobota: 06:00-22:00<br/>Niedziela: Nieczynne"]},{"id":"39","label":"Bułgarska 121/123","address":"Bułgarska 121/123","city":"Poznań","longitude":16.868523,"latitude":52.411281,"popupLines":["Poniedziałek: 06:00-23:00<br/>Wtorek: 06:00-23:00<br/>Środa: 06:00-23:00<br/>Czwartek: 06:00-23:00<br/>Piątek: 06:00-23:00<br/>Sobota: 06:00-23:00<br/>Niedziela: Nieczynne"]},{"id":"65","label":"Dąbrowskiego 399","address":"Dąbrowskiego 399","city":"Poznań","longitude":16.832789,"latitude":52.432562,"popupLines":["Poniedziałek: 06:00-23:00<br/>Wtorek: 06:00-23:00<br/>Środa: 06:00-23:00<br/>Czwartek: 06:00-23:00<br/>Piątek: 06:00-23:00<br/>Sobota: 06:00-23:00<br/>Niedziela: Nieczynne"]},{"id":"85","label":"Marcelińska 77","address":"Marcelińska 77","city":"Poznań","longitude":16.874044,"latitude":52.404605,"popupLines":["Poniedziałek: 06:00-22:00<br/>Wtorek: 06:00-22:00<br/>Środa: 06:00-22:00<br/>Czwartek: 06:00-22:00<br/>Piątek: 06:00-22:00<br/>Sobota: 06:00-22:00<br/>Niedziela: Nieczynne"]},{"id":"86","label":"Matejki 62","address":"Matejki 62","city":"Poznań","longitude":16.899224,"latitude":52.402074,"popupLines":["Poniedziałek: Nieczynne<br/>Wtorek: Nieczynne<br/>Środa: Nieczynne<br/>Czwartek: Nieczynne<br/>Piątek: Nieczynne<br/>Sobota: Nieczynne<br/>Niedziela: Nieczynne"]},{"id":"87","label":"Szadecka 2","address":"Szadecka 2","city":"Poznań","longitude":16.852988,"latitude":52.386265,"popupLines":["Poniedziałek: 06:15-23:00<br/>Wtorek: 06:15-23:00<br/>Środa: 06:15-23:00<br/>Czwartek: 06:15-23:00<br/>Piątek: 06:15-23:00<br/>Sobota: 06:15-23:00<br/>Niedziela: Nieczynne"]},{"id":"88","label":"Sokoła 26","address":"Sokoła 26","city":"Poznań","longitude":16.91177,"latitude":52.426328,"popupLines":["Poniedziałek: 06:00-23:00<br/>Wtorek: 06:00-23:00<br/>Środa: 06:00-23:00<br/>Czwartek: 06:00-23:00<br/>Piątek: 06:00-23:00<br/>Sobota: 06:00-23:00<br/>Niedziela: Nieczynne"]},{"id":"898","label":"Kościelna 30","address":"Kościelna 30","city":"Poznań","longitude":16.906027,"latitude":52.415126,"popupLines":["Poniedziałek: 06:00-22:30<br/>Wtorek: 06:00-22:30<br/>Środa: 06:00-22:30<br/>Czwartek: 06:00-22:30<br/>Piątek: 06:00-22:30<br/>Sobota: 06:00-22:30<br/>Niedziela: Nieczynne"]},{"id":"98","label":"os. Piastowskie 22","address":"os. Piastowskie 22","city":"Poznań","longitude":16.944958,"latitude":52.394748,"popupLines":["Poniedziałek: 06:00-23:30<br/>Wtorek: 06:00-23:30<br/>Środa: 06:00-23:30<br/>Czwartek: 06:00-23:30<br/>Piątek: 06:00-23:30<br/>Sobota: 06:00-23:30<br/>Niedziela: Nieczynne"]},{"id":"99","label":"os. Jagiellońskie 14","address":"os. Jagiellońskie 14","city":"Poznań","longitude":16.951013,"latitude":52.392879,"popupLines":["Poniedziałek: 06:00-23:30<br/>Wtorek: 06:00-23:30<br/>Środa: 06:00-23:30<br/>Czwartek: 06:00-23:30<br/>Piątek: 06:00-23:30<br/>Sobota: 06:00-23:30<br/>Niedziela: Nieczynne"]},{"id":"996","label":"pl. Wiosny Ludów 2","address":"pl. Wiosny Ludów 2","city":"Poznań","longitude":16.932532,"latitude":52.405178,"popupLines":["Poniedziałek: 06:00-22:00<br/>Wtorek: 06:00-22:00<br/>Środa: 06:00-22:00<br/>Czwartek: 06:00-22:00<br/>Piątek: 06:00-22:00<br/>Sobota: 06:00-22:00<br/>Niedziela: Nieczynne"]},{"id":"998","label":"Dąbrowskiego 29","address":"Dąbrowskiego 29","city":"Poznań","longitude":16.908382,"latitude":52.411881,"popupLines":["Poniedziałek: 06:00-23:30<br/>Wtorek: 06:00-23:30<br/>Środa: 06:00-23:30<br/>Czwartek: 06:00-23:30<br/>Piątek: 06:00-23:30<br/>Sobota: 06:00-23:30<br/>Niedziela: Nieczynne"]}]